odoo/addons/hide_invoice_shipping_address/README.rst
odoo/addons/hide_invoice_shipping_address/__init__.py
odoo/addons/hide_invoice_shipping_address/__manifest__.py
odoo/addons/hide_invoice_shipping_address/i18n/ca_ES.po
odoo/addons/hide_invoice_shipping_address/i18n/es.po
odoo/addons/hide_invoice_shipping_address/models/__init__.py
odoo/addons/hide_invoice_shipping_address/models/account_move.py
odoo/addons/hide_invoice_shipping_address/models/res_company.py
odoo/addons/hide_invoice_shipping_address/models/res_config_settings.py
odoo/addons/hide_invoice_shipping_address/models/res_partner.py
odoo/addons/hide_invoice_shipping_address/report/report_invoice.xml
odoo/addons/hide_invoice_shipping_address/static/description/icon.png
odoo/addons/hide_invoice_shipping_address/views/account_move_view.xml
odoo/addons/hide_invoice_shipping_address/views/res_config_settings_view.xml
odoo/addons/hide_invoice_shipping_address/views/res_partner_view.xml
odoo14_addon_hide_invoice_shipping_address-14.0.1.0.1.dev1.dist-info/METADATA
odoo14_addon_hide_invoice_shipping_address-14.0.1.0.1.dev1.dist-info/WHEEL
odoo14_addon_hide_invoice_shipping_address-14.0.1.0.1.dev1.dist-info/top_level.txt
odoo14_addon_hide_invoice_shipping_address-14.0.1.0.1.dev1.dist-info/RECORD
