Metadata-Version: 2.1
Name: odoo14-addon-hide_invoice_shipping_address
Version: 14.0.1.0.1.dev1
Summary: Keep the shipping address hidden on the invoice.
Home-page: https://www.sygel.es
Author: Sygel, Odoo Community Association (OCA)
Author-email: support@odoo-community.org
Classifier: Programming Language :: Python
Classifier: Framework :: Odoo
Classifier: Framework :: Odoo :: 14.0
Requires-Python: >=3.6
Requires-Dist: odoo<14.1dev,>=14.0a
